src/__init__.py
src/benchmark.py
src/cli/__init__.py
src/cli/benchmark_cmd.py
src/cli/compile_cmd.py
src/cli/dry_run_cmd.py
src/cli/entrypoint.py
src/compiler_handler.py
src/file_handler.py
src/helpers.py
src/logging_setup.py
src/wrappers.py
pycompile-0.2.3.dist-info/LICENSE
pycompile-0.2.3.dist-info/METADATA
pycompile-0.2.3.dist-info/WHEEL
pycompile-0.2.3.dist-info/entry_points.txt
pycompile-0.2.3.dist-info/RECORD
