Metadata-Version: 2.1
Name: pycompile
Version: 0.2.3
Summary: A CLI tool for compiling python
Home-page: https://github.com/iplitharas/pycompile
License: MIT
Author: iplitharas
Author-email: johnplitharas@gmail.com
Requires-Python: >=3.10
Classifier: License :: OSI Approved :: MIT License
Classifier: Programming Language :: Python :: 3
Classifier: Programming Language :: Python :: 3.10
Classifier: Programming Language :: Python :: 3.11
Classifier: Programming Language :: Python :: 3.12
Classifier: Programming Language :: Python :: 3.13
Requires-Dist: click (>=8.1.3,<9.0.0)
Requires-Dist: cython (>=3.0.0,<4.0.0)
Requires-Dist: memory-profiler (>=0.61.0,<0.62.0)
Requires-Dist: nuitka (>=1.7.5,<3.0.0)
Requires-Dist: pytest-benchmark (>=4.0.0,<5.0.0)
Requires-Dist: tqdm (>=4.64.1,<5.0.0)
Project-URL: Documentation, https://iplitharas.github.io/pycompile/
Project-URL: Repository, https://github.com/iplitharas/pycompile
